autopr/__init__.py
autopr/analysis.py
autopr/ci_parser.py
autopr/cli.py
autopr/coverage_utils.py
autopr/generator.py
autopr/issue_validator.py
autopr/lint.py
autopr/llm.py
autopr/main.py
autopr/parser.py
autopr/prompts.py
autopr/providers.py
autopr/reviewer.py
autopr/validators.py
autopr_core-0.4.1b0.dist-info/licenses/LICENSE
autopr_core-0.4.1b0.dist-info/METADATA
autopr_core-0.4.1b0.dist-info/WHEEL
autopr_core-0.4.1b0.dist-info/entry_points.txt
autopr_core-0.4.1b0.dist-info/top_level.txt
autopr_core-0.4.1b0.dist-info/RECORD
