Metadata-Version: 2.4
Name: autopr-core
Version: 0.4.1b0
Summary: AI-powered Pull Request Generator & Reviewer - Automate PR titles, descriptions, and code reviews
Author-email: AutoPR Team <autopr@example.com>
Maintainer-email: AutoPR Team <autopr@example.com>
License: MIT
Project-URL: Homepage, https://github.com/surenkotian/AutoPR
Project-URL: Documentation, https://autopr.readthedocs.io/
Project-URL: Repository, https://github.com/surenkotian/AutoPR
Project-URL: Issues, https://github.com/surenkotian/AutoPR/issues
Project-URL: Changelog, https://github.com/surenkotian/AutoPR/blob/main/CHANGELOG.md
Keywords: ai,pull-request,code-review,automation,github,git
Classifier: Development Status :: 4 - Beta
Classifier: Intended Audience :: Developers
Classifier: License :: OSI Approved :: MIT License
Classifier: Operating System :: OS Independent
Classifier: Programming Language :: Python :: 3
Classifier: Programming Language :: Python :: 3.8
Classifier: Programming Language :: Python :: 3.9
Classifier: Programming Language :: Python :: 3.10
Classifier: Programming Language :: Python :: 3.11
Classifier: Programming Language :: Python :: 3.12
Classifier: Topic :: Software Development :: Quality Assurance
Classifier: Topic :: Software Development :: Version Control :: Git
Requires-Python: >=3.8
License-File: LICENSE
Requires-Dist: fastapi>=0.92.0
Requires-Dist: uvicorn[standard]>=0.20.0
Requires-Dist: httpx>=0.24.0
Requires-Dist: click>=8.1.0
Requires-Dist: pytest>=7.0.0
Requires-Dist: openai>=1.0.0
Requires-Dist: anthropic<1.0.0,>=0.75.0
Requires-Dist: python-dotenv>=1.0.0
Requires-Dist: loguru>=0.7.0
Requires-Dist: questionary>=2.0.0
Dynamic: license-file
